setup.py
weather2stats/__init__.py
weather2stats/common.py
weather2stats/to-graphite.py
weather2stats/to_influx.py
weather2stats.egg-info/PKG-INFO
weather2stats.egg-info/SOURCES.txt
weather2stats.egg-info/dependency_links.txt
weather2stats.egg-info/entry_points.txt
weather2stats.egg-info/requires.txt
weather2stats.egg-info/top_level.txt
weather2stats/plugins/__init__.py
weather2stats/plugins/opensensemap.py
weather2stats/plugins/openweathermap.py
weather2stats/plugins/stadtklima-stuttgart.py