Metadata-Version: 1.0
Name: weather2stats
Version: 0.2
Summary: Convert stats websites to influx data
Home-page: https://github.com/makefu/weather2stats
Author: Felix Richter
Author-email: github@syntax-fehler.de
License: WTFPL
Keywords: api
Platform: UNKNOWN
